odoo9_addon_account_bank_statement_import_camt-9.0.1.0.0-py2.7-nspkg.pth
odoo_addons/account_bank_statement_import_camt/__openerp__.py
odoo_addons/account_bank_statement_import_camt/camt.py
odoo_addons/account_bank_statement_import_camt/__init__.py
odoo_addons/account_bank_statement_import_camt/README.rst
odoo_addons/account_bank_statement_import_camt/models/account_bank_statement_import.py
odoo_addons/account_bank_statement_import_camt/models/__init__.py
odoo_addons/account_bank_statement_import_camt/i18n/es.po
odoo_addons/account_bank_statement_import_camt/i18n/lt_LT.po
odoo_addons/account_bank_statement_import_camt/i18n/sl.po
odoo_addons/account_bank_statement_import_camt/i18n/pt_PT.po
odoo_addons/account_bank_statement_import_camt/i18n/nl.po
odoo_addons/account_bank_statement_import_camt/i18n/de.po
odoo_addons/account_bank_statement_import_camt/i18n/fr.po
odoo_addons/account_bank_statement_import_camt/i18n/pt_BR.po
odoo_addons/account_bank_statement_import_camt/views/account_bank_statement_import.xml
odoo_addons/account_bank_statement_import_camt/test_files/test-camt053
odoo_addons/account_bank_statement_import_camt/test_files/test-camt053.zip
odoo_addons/account_bank_statement_import_camt/tests/__init__.py
odoo_addons/account_bank_statement_import_camt/tests/test_import_bank_statement.py
odoo_addons/account_bank_statement_import_camt/demo/demo_data.xml
odoo9_addon_account_bank_statement_import_camt-9.0.1.0.0.dist-info/top_level.txt
odoo9_addon_account_bank_statement_import_camt-9.0.1.0.0.dist-info/WHEEL
odoo9_addon_account_bank_statement_import_camt-9.0.1.0.0.dist-info/RECORD
odoo9_addon_account_bank_statement_import_camt-9.0.1.0.0.dist-info/metadata.json
odoo9_addon_account_bank_statement_import_camt-9.0.1.0.0.dist-info/DESCRIPTION.rst
odoo9_addon_account_bank_statement_import_camt-9.0.1.0.0.dist-info/METADATA
odoo9_addon_account_bank_statement_import_camt-9.0.1.0.0.dist-info/namespace_packages.txt
