Metadata-Version: 2.0
Name: odoo9-addon-account-bank-statement-import-camt
Version: 9.0.1.0.0
Summary: CAMT Format Bank Statements Import
Home-page: https://github.com/OCA/bank-statement-import
Author: Odoo Community Association (OCA), Therp BV
Author-email: support@odoo-community.org
License: AGPL-3
Platform: UNKNOWN
Requires-Dist: odoo (<9.1a,>=9.0a)
Classifier: Programming Language :: Python :: 2.7
Classifier: Framework :: Odoo
Classifier: License :: OSI Approved :: GNU Affero General Public License v3
